caffeination/__init__.py
caffeination/caffeination.py
caffeination-0.1.dist-info/LICENSE.txt
caffeination-0.1.dist-info/METADATA
caffeination-0.1.dist-info/WHEEL
caffeination-0.1.dist-info/entry_points.txt
caffeination-0.1.dist-info/top_level.txt
caffeination-0.1.dist-info/RECORD
